HTest/HTMLTestRunner.py
HTest/__init__.py
HTest/__main__.py
HTest/basepage.py
HTest/cli.py
HTest/exception.py
HTest/factory_random.py
HTest/get_excel.py
HTest/get_yaml.py
HTest/globalvar.py
HTest/loader.py
HTest/log.py
HTest/logger.py
HTest/new_report.py
HTest/operate.py
HTest/run_all.py
HTest/run_yaml.py
HTest/runner.py
HTest/send_email.py
HTest/setting.py
HTest/testcase.py
HTest/content/case.png
HTest/content/config.png
HTest/content/data.yaml
HTest/content/email.png
HTest/content/step.png
HTest/content/suit.png
HTest/content/报告.png
HTest/content/项目目录.png
HTest/content/screenshots/01.png
HTest/content/screenshots/02.png
HTest/content/screenshots/03.png
HTest/verificationcode/PC_point.py
HTest/verificationcode/__init__.py
HTest/verificationcode/code.py
HTest/verificationcode/mouse.py
HTest/verificationcode/point.py
HTest-0.3.0.dist-info/LICENSE
HTest-0.3.0.dist-info/METADATA
HTest-0.3.0.dist-info/WHEEL
HTest-0.3.0.dist-info/entry_points.txt
HTest-0.3.0.dist-info/top_level.txt
HTest-0.3.0.dist-info/RECORD
