Metadata-Version: 2.1
Name: HTest
Version: 0.3.0
Summary: Automated testing framework based on unittest.
Home-page: https://github.com/Tao99/ui-autotest
Author: Tao lei
Author-email: 1285642171@qq.com
License: BSD
Platform: UNKNOWN
Classifier: Intended Audience :: Developers
Classifier: License :: OSI Approved :: BSD License
Classifier: Operating System :: OS Independent
Classifier: Programming Language :: Python
Classifier: Programming Language :: Python :: 3.7
Classifier: Topic :: Software Development :: Testing
Requires-Python: >=3.7
Requires-Dist: Faker (==9.8.2)
Requires-Dist: Pillow (==5.4.1)
Requires-Dist: PyAutoGUI (==0.9.53)
Requires-Dist: PyYAML (==5.4.1)
Requires-Dist: ddt (==1.4.2)
Requires-Dist: numpy (==1.21.3)
Requires-Dist: opencv-python (==4.5.4.58)
Requires-Dist: openpyxl (==3.0.9)
Requires-Dist: pytesseract (==0.3.8)
Requires-Dist: setuptools (==40.8.0)
